dddesign/__init__.py
dddesign/components/__init__.py
dddesign/components/domains/__init__.py
dddesign/components/domains/dto/__init__.py
dddesign/components/domains/dto/errors.py
dddesign/components/domains/value_objects/__init__.py
dddesign/components/domains/value_objects/auto_uuid.py
dddesign/components/domains/value_objects/error.py
dddesign/py.typed
dddesign/structure/__init__.py
dddesign/structure/applications/__init__.py
dddesign/structure/applications/application.py
dddesign/structure/applications/application_factory.py
dddesign/structure/domains/__init__.py
dddesign/structure/domains/aggregates/__init__.py
dddesign/structure/domains/aggregates/aggregate.py
dddesign/structure/domains/aggregates/aggregate_list_factory.py
dddesign/structure/domains/constants/__init__.py
dddesign/structure/domains/constants/base_enum.py
dddesign/structure/domains/constants/choice_enum.py
dddesign/structure/domains/dto/__init__.py
dddesign/structure/domains/dto/dto.py
dddesign/structure/domains/entities/__init__.py
dddesign/structure/domains/entities/entity.py
dddesign/structure/domains/errors/__init__.py
dddesign/structure/domains/errors/base_error.py
dddesign/structure/domains/errors/collection_error.py
dddesign/structure/domains/value_objects/__init__.py
dddesign/structure/domains/value_objects/value_object.py
dddesign/structure/infrastructure/__init__.py
dddesign/structure/infrastructure/adapters/__init__.py
dddesign/structure/infrastructure/adapters/external/__init__.py
dddesign/structure/infrastructure/adapters/external/external_adapter.py
dddesign/structure/infrastructure/adapters/internal/__init__.py
dddesign/structure/infrastructure/adapters/internal/internal_adapter.py
dddesign/structure/infrastructure/repositories/__init__.py
dddesign/structure/infrastructure/repositories/repository.py
dddesign/structure/services/__init__.py
dddesign/structure/services/service.py
dddesign/unittest/__init__.py
dddesign/unittest/magic_mock.py
dddesign/utils/__init__.py
dddesign-1.1.9.dist-info/METADATA
dddesign-1.1.9.dist-info/WHEEL
dddesign-1.1.9.dist-info/licenses/LICENSE
dddesign-1.1.9.dist-info/RECORD
