Metadata-Version: 2.4
Name: dddesign
Version: 1.1.9
Summary: Domain Driven Design Library
License: MIT
License-File: LICENSE
Keywords: python,ddd,domain driven design,ddd architecture,ddd structure,architecture,structure,dddesign
Author: davyddd
Requires-Python: >=3.9,<3.14
Classifier: License :: OSI Approved :: MIT License
Classifier: Programming Language :: Python :: 3
Classifier: Programming Language :: Python :: 3.9
Classifier: Programming Language :: Python :: 3.10
Classifier: Programming Language :: Python :: 3.11
Classifier: Programming Language :: Python :: 3.12
Classifier: Programming Language :: Python :: 3.13
Requires-Dist: ddutils (<0.2.0)
Requires-Dist: idna (>=3.7,<4.0)
Requires-Dist: pydantic (>=2.1,<2.13)
Requires-Dist: setuptools (>=78.1.1)
Project-URL: Repository, https://github.com/davyddd/dddesign
